technologydata/__init__.py
technologydata/datapackage.py
technologydata/parameter.py
technologydata/source.py
technologydata/source_collection.py
technologydata/technology.py
technologydata/technology_collection.py
technologydata/constants/__init__.py
technologydata/constants/energy_density.py
technologydata/package_data/dea_energy_storage/dea_energy_storage.py
technologydata/package_data/dea_energy_storage/sources.json
technologydata/package_data/dea_energy_storage/technologies.json
technologydata/package_data/raw/Technology_datasheet_for_energy_storage.xlsx
technologydata/technologies/__init__.py
technologydata/technologies/growth_models.py
technologydata/utils/__init__.py
technologydata/utils/carriers.txt
technologydata/utils/commons.py
technologydata/utils/heating_values.txt
technologydata/utils/units.py
technologydata-0.1.0.dist-info/licenses/LICENSE
technologydata-0.1.0.dist-info/METADATA
technologydata-0.1.0.dist-info/WHEEL
technologydata-0.1.0.dist-info/top_level.txt
technologydata-0.1.0.dist-info/RECORD
