Metadata-Version: 2.4
Name: technologydata
Version: 0.1.0
Summary: Package for providing common data assumptions for energy system modelling on techno-economics and macro-economics.
Author-email: Contributors to technologydata <johannes.hampp@openenergytransition.org>, Contributors to technologydata <fabrizio.finozzi.business@gmail.com>
Project-URL: Homepage, https://github.com/open-energy-transition/technology-data
Project-URL: Source, https://github.com/open-energy-transition/technology-data
Project-URL: BugTracker, https://github.com/open-energy-transition/technology-data/issues
Project-URL: Changelog, https://github.com/open-energy-transition/technology-data/releases
Keywords: energy,modelling,techno-economics,macroeconomics
Classifier: Programming Language :: Python :: 3.12
Classifier: Programming Language :: Python :: 3.13
Classifier: Development Status :: 3 - Alpha
Classifier: Environment :: Console
Classifier: Intended Audience :: Science/Research
Classifier: Natural Language :: English
Classifier: Operating System :: OS Independent
Requires-Python: >=3.12
License-File: LICENSE
Requires-Dist: frozendict>=2.4.6
Requires-Dist: hdx-python-country>=3.9.6
Requires-Dist: mypy>=1.15.0
Requires-Dist: pandas>=2.2.3
Requires-Dist: pint>=0.24.4
Requires-Dist: pydantic>=2.11.7
Requires-Dist: pydeflate>=2.3.3
Requires-Dist: requests>=2.32.3
Requires-Dist: savepagenow>=1.3.0
Requires-Dist: scipy>=1.16.1
Dynamic: license-file
